{
  "project_info": {
    "project_number": "18703598441",
    "project_id": "tomaramosuandesandroid",
    "storage_bucket": "tomaramosuandesandroid.appspot.com"
  },
  "client": [
    {
      "client_info": {
        "mobilesdk_app_id": "1:18703598441:android:67899a5a2b54735205f3f8",
        "android_client_info": {
          "package_name": "com.ifgarces.tomaramosuandes"
        }
      },
      "oauth_client": [
        {
          "client_id": "18703598441-rqeqccfesn2d6os6q3sr2pnmhkgj1chk.apps.googleusercontent.com",
          "client_type": 3
        }
      ],
      "api_key": [
        {
          "current_key": "AIzaSyAHZ6YoJ1qzIRe86ofJbLhDVaZBXyPFCVY"
        }
      ],
      "services": {
        "appinvite_service": {
          "other_platform_oauth_client": [
            {
              "client_id": "18703598441-rqeqccfesn2d6os6q3sr2pnmhkgj1chk.apps.googleusercontent.com",
              "client_type": 3
            }
          ]
        }
      }
    }
  ],
  "configuration_version": "1"
}